discord/__init__.py
discord/__main__.py
discord/abc.py
discord/activity.py
discord/appinfo.py
discord/asset.py
discord/audit_logs.py
discord/backoff.py
discord/calls.py
discord/channel.py
discord/client.py
discord/colour.py
discord/context_managers.py
discord/embeds.py
discord/emoji.py
discord/enums.py
discord/errors.py
discord/file.py
discord/flags.py
discord/gateway.py
discord/guild.py
discord/http.py
discord/integrations.py
discord/invite.py
discord/iterators.py
discord/member.py
discord/mentions.py
discord/message.py
discord/mixins.py
discord/object.py
discord/oggparse.py
discord/opus.py
discord/partial_emoji.py
discord/permissions.py
discord/player.py
discord/raw_models.py
discord/reaction.py
discord/relationship.py
discord/role.py
discord/shard.py
discord/state.py
discord/sticker.py
discord/team.py
discord/template.py
discord/user.py
discord/utils.py
discord/voice_client.py
discord/webhook.py
discord/widget.py
discord/bin/libopus-0.x64.dll
discord/bin/libopus-0.x86.dll
discord/ext/commands/__init__.py
discord/ext/commands/_types.py
discord/ext/commands/bot.py
discord/ext/commands/cog.py
discord/ext/commands/context.py
discord/ext/commands/converter.py
discord/ext/commands/cooldowns.py
discord/ext/commands/core.py
discord/ext/commands/errors.py
discord/ext/commands/help.py
discord/ext/commands/view.py
discord/ext/tasks/__init__.py
maxcord.py-1.0.dist-info/LICENSE
maxcord.py-1.0.dist-info/METADATA
maxcord.py-1.0.dist-info/WHEEL
maxcord.py-1.0.dist-info/top_level.txt
maxcord.py-1.0.dist-info/RECORD
